arcor2_arserver_data/VERSION
arcor2_arserver_data/__init__.py
arcor2_arserver_data/client.py
arcor2_arserver_data/objects.py
arcor2_arserver_data/py.typed
arcor2_arserver_data/robot.py
arcor2_arserver_data/events/__init__.py
arcor2_arserver_data/events/actions.py
arcor2_arserver_data/events/common.py
arcor2_arserver_data/events/lock.py
arcor2_arserver_data/events/objects.py
arcor2_arserver_data/events/project.py
arcor2_arserver_data/events/robot.py
arcor2_arserver_data/events/scene.py
arcor2_arserver_data/rpc/__init__.py
arcor2_arserver_data/rpc/build.py
arcor2_arserver_data/rpc/camera.py
arcor2_arserver_data/rpc/common.py
arcor2_arserver_data/rpc/lock.py
arcor2_arserver_data/rpc/objects.py
arcor2_arserver_data/rpc/project.py
arcor2_arserver_data/rpc/robot.py
arcor2_arserver_data/rpc/scene.py
arcor2_arserver_data/rpc/user.py
arcor2_arserver_data-1.1.0.dist-info/METADATA
arcor2_arserver_data-1.1.0.dist-info/WHEEL
arcor2_arserver_data-1.1.0.dist-info/namespace_packages.txt
arcor2_arserver_data-1.1.0.dist-info/top_level.txt
arcor2_arserver_data-1.1.0.dist-info/RECORD
